airless/google/cloud/secret_manager/__init__.py
airless/google/cloud/secret_manager/hook/__init__.py
airless/google/cloud/secret_manager/hook/secret_manager.py
airless_google_cloud_secret_manager-0.3.0.dist-info/METADATA
airless_google_cloud_secret_manager-0.3.0.dist-info/WHEEL
airless_google_cloud_secret_manager-0.3.0.dist-info/top_level.txt
airless_google_cloud_secret_manager-0.3.0.dist-info/RECORD
