Metadata-Version: 2.4
Name: airless-google-cloud-secret-manager
Version: 0.3.0
Summary: Airless package to manage google secret manager
License: MIT License
Project-URL: Homepage, https://github.com/astercapital/airless
Project-URL: Bug Tracker, https://github.com/astercapital/airless/issues
Requires-Python: >=3.9
Requires-Dist: google-cloud-secret-manager<3.0.0,>=2.12.6
Requires-Dist: airless-core>=0.2.1
